githublfs/__init__.py
githublfs-0.2.1.dist-info/WHEEL
githublfs-0.2.1.dist-info/METADATA
githublfs-0.2.1.dist-info/RECORD
