Metadata-Version: 2.3
Name: githublfs
Version: 0.2.1
Summary: Simple library to commit lfs files to Github repos
Keywords: Github,LFS
Author: Anès Foufa
Author-email: Anès Foufa <anes.foufa@upply.com>
License: MIT
Classifier: Topic :: Software Development :: Version Control
Classifier: Topic :: Software Development :: Version Control :: Git
Classifier: Programming Language :: Python :: 3
Classifier: Programming Language :: Python :: 3.8
Classifier: Programming Language :: Python :: 3.9
Classifier: Programming Language :: Python :: 3.10
Classifier: Programming Language :: Python :: 3.11
Classifier: Programming Language :: Python :: 3.12
Classifier: Programming Language :: Python :: 3.13
Requires-Dist: pygithub>=1.55
Requires-Dist: requests>=2.28.1
Requires-Dist: mypy>=1.10 ; extra == 'dev'
Requires-Dist: ruff>=0.11.0 ; extra == 'dev'
Requires-Dist: twine>=4.0.1 ; extra == 'dev'
Requires-Dist: requests-mock>=1.9.3 ; extra == 'dev'
Requires-Dist: pytest>=7.1.2 ; extra == 'dev'
Requires-Python: >=3.8
Project-URL: Homepage, https://github.com/AnesFoufa/githublfs
Provides-Extra: dev
